{"template":"__react_static_root__/src/containers/Type","sharedHashesByProp":{"typeNames":"Axdi","pokemonIcons":"cnQr7"},"data":{"dishes":[{"dish_name":"Brain Food a la Cube","dish_img_x":-613,"dish_img_y":-264,"pokemon":[{"name":"Abra","qualities":["Normal"]},{"name":"Slowpoke","qualities":["Very Good","Good"]},{"name":"Drowzee","qualities":["Special","Very Good","Good"]},{"name":"Exeggcute","qualities":["Very Good","Good"]},{"name":"Mr. Mime","qualities":["Special","Very Good","Good"]},{"name":"Jynx","qualities":["Special","Very Good","Good"]}],"qualities":[{"quality":"Special","pokemon":[{"name":"Drowzee","attr_rate":80},{"name":"Mr. Mime","attr_rate":10},{"name":"Jynx","attr_rate":10}],"recipes":[]},{"quality":"Very Good","pokemon":[{"name":"Slowpoke","attr_rate":33.33},{"name":"Drowzee","attr_rate":26.67},{"name":"Exeggcute","attr_rate":33.33},{"name":"Mr. Mime","attr_rate":3.33},{"name":"Jynx","attr_rate":3.33}],"recipes":[["bb","a","ir","h","h"]]},{"quality":"Good","pokemon":[{"name":"Slowpoke","attr_rate":48.78},{"name":"Drowzee","attr_rate":1.95},{"name":"Exeggcute","attr_rate":48.78},{"name":"Mr. Mime","attr_rate":0.24},{"name":"Jynx","attr_rate":0.24}],"recipes":[["bb","bb","h","a","a"],["bb","bb","h","a","f"],["bb","a","f","h","h"],["bb","bb","a","ir","h"]]},{"quality":"Normal","pokemon":[{"name":"Abra","attr_rate":100}],"recipes":[["bb","bb","bb","a","a"],["bb","bb","bb","a","f"]]}]}]},"path":"types/brain-food-a-la-cube"}
